README.md
setup.py
wanglb_utils/recordstate.py
wanglb_utils/utils_func.py
wanglb_utils.egg-info/PKG-INFO
wanglb_utils.egg-info/SOURCES.txt
wanglb_utils.egg-info/dependency_links.txt
wanglb_utils.egg-info/entry_points.txt
wanglb_utils.egg-info/requires.txt
wanglb_utils.egg-info/top_level.txt